[
    {
        "healing": {
            "Boiled Egg": 10,
            "Chicken Nugget": 15,
            "Chocolate": 15,
            "Marshmallow": 5,
            "Watermelon": 20,
            "Lollipop": 25,
            "Broccoli": 45,
            "Ice Cream": 500,
            "Oreos": 40,
            "Coca Cola": 50,
            "Cheesecake": 100,

        
        },
        "attack": {
            "Salt": 5,
            "Pot of boil water": 10,
            "Pepper": 15,
            "Chicken": 10,
            "Egg Fried Rice": 200,
            "Cheese Stick": 100,
            "School Pizza": 200,
            "Dominos Pizza": 120,
            "Apple Pie": 100,
            "California Reaper": 1500,
            


        },
        "buff": {
            "Vitanims": 1,
            "Coffee": 2,
            "Sugar Cube I thinking????": 3,
            "Steak": 20,
            "Milk": 50,
            "Koolaid": 25,
            "Doritos": 25,
            "Mountain Dew": 150,


        }
    }
]